latinex_sdk/__init__.py
latinex_sdk/generic_utils.py
latinex_sdk-0.1.6.dist-info/LICENSE
latinex_sdk-0.1.6.dist-info/METADATA
latinex_sdk-0.1.6.dist-info/WHEEL
latinex_sdk-0.1.6.dist-info/top_level.txt
latinex_sdk-0.1.6.dist-info/RECORD
