Metadata-Version: 2.1
Name: latinex-sdk
Version: 0.1.6
Summary: Software Development Kit for Latinex (https://www.latinexbolsa.com)
Author: Blasser Analytica (Rodolfo Blasser)
Author-email: <rodolfoblasser@gmail.com>
Keywords: python,panama,finance,stocks,fixed income,data,api,market data,latinex
Classifier: Development Status :: 1 - Planning
Classifier: Intended Audience :: Developers
Classifier: Programming Language :: Python :: 3
Classifier: Operating System :: Unix
Classifier: Operating System :: MacOS :: MacOS X
Classifier: Operating System :: Microsoft :: Windows
License-File: LICENSE
Requires-Dist: requests
Requires-Dist: pandas
Requires-Dist: urllib3
